micropython_mpl3115a2/__init__.py
micropython_mpl3115a2/i2c_helpers.py
micropython_mpl3115a2/mpl3115a2.py
micropython_mpl3115a2-0.1.0.dist-info/LICENSE
micropython_mpl3115a2-0.1.0.dist-info/METADATA
micropython_mpl3115a2-0.1.0.dist-info/WHEEL
micropython_mpl3115a2-0.1.0.dist-info/top_level.txt
micropython_mpl3115a2-0.1.0.dist-info/RECORD
