Metadata-Version: 2.1
Name: micropython-mpl3115a2
Version: 0.1.0
Summary: MicroPython driver for the NXP MPL3115A2 Pressure and Temperature sensor
Author-email: JDM <xxyx@mailmeto.mozmail.com>
License: MIT
Project-URL: Homepage, https://github.com/jposada202020/MicroPython_MPL3115A2
Keywords: sensor,micropython,mpl3115a2,micropython,nxp,temperature,pressure,mpl3115a2,sensor,driver
Classifier: Intended Audience :: Developers
Classifier: Topic :: Software Development :: Libraries
Classifier: Topic :: Software Development :: Embedded Systems
Classifier: Topic :: System :: Hardware
Classifier: License :: OSI Approved :: MIT License
Classifier: Programming Language :: Python :: Implementation :: MicroPython
License-File: LICENSE
